google_sheets_tools.py
google_sheets_tools-0.0.2.dist-info/WHEEL
google_sheets_tools-0.0.2.dist-info/METADATA
google_sheets_tools-0.0.2.dist-info/RECORD
