Metadata-Version: 2.1
Name: google-sheets-tools
Version: 0.0.2
Summary: The package is used for work with the Google Sheet spreadsheets using their URL.
Author: Bohdan Salamakha
Author-email: allen.avanheim@gmail.com
Requires-Python: >=3.10,<4.0
Classifier: Programming Language :: Python :: 3
Classifier: Programming Language :: Python :: 3.10
Requires-Dist: bs4 (>=0.0.1,<0.0.2)
Requires-Dist: requests (>=2.28.1,<3.0.0)
